lektor_creative_commons/__init__.py
lektor_creative_commons/plugin.py
lektor_creative_commons/translation.py
lektor_creative_commons/assets/by/4.0/80x15.png
lektor_creative_commons/assets/by/4.0/88x31.png
lektor_creative_commons/assets/by-nc/4.0/80x15.png
lektor_creative_commons/assets/by-nc/4.0/88x31.png
lektor_creative_commons/assets/by-nc-nd/4.0/80x15.png
lektor_creative_commons/assets/by-nc-nd/4.0/88x31.png
lektor_creative_commons/assets/by-nc-sa/4.0/80x15.png
lektor_creative_commons/assets/by-nc-sa/4.0/88x31.png
lektor_creative_commons/assets/by-nd/4.0/80x15.png
lektor_creative_commons/assets/by-nd/4.0/88x31.png
lektor_creative_commons/assets/by-sa/4.0/80x15.png
lektor_creative_commons/assets/by-sa/4.0/88x31.png
lektor_creative_commons/locales/de/LC_MESSAGES/messages.mo
lektor_creative_commons/locales/en/LC_MESSAGES/messages.mo
lektor_creative_commons/locales/pt_BR/LC_MESSAGES/messages.mo
lektor_creative_commons-0.6.0.data/data/lektor_creative_commons/locales/de/LC_MESSAGES/messages.mo
lektor_creative_commons-0.6.0.data/data/lektor_creative_commons/locales/en/LC_MESSAGES/messages.mo
lektor_creative_commons-0.6.0.data/data/lektor_creative_commons/locales/pt_BR/LC_MESSAGES/messages.mo
lektor_creative_commons-0.6.0.dist-info/LICENSE
lektor_creative_commons-0.6.0.dist-info/METADATA
lektor_creative_commons-0.6.0.dist-info/WHEEL
lektor_creative_commons-0.6.0.dist-info/entry_points.txt
lektor_creative_commons-0.6.0.dist-info/top_level.txt
lektor_creative_commons-0.6.0.dist-info/RECORD
