Metadata-Version: 2.1
Name: lektor-creative-commons
Version: 0.6.0
Summary: Lektor plugin to add Creative Commons license to your pages
Home-page: https://github.com/humrochagf/lektor-creative-commons
Author: Humberto Rocha
Author-email: humrochagf@gmail.com
License: MIT
Project-URL: Documentation, https://github.com/humrochagf/lektor-creative-commons/blob/master/README.md
Project-URL: Source, https://github.com/humrochagf/lektor-creative-commons/
Project-URL: Tracker, https://github.com/humrochagf/lektor-creative-commons/issues
Platform: UNKNOWN
Classifier: Framework :: Lektor
Classifier: Environment :: Plugins
